pogger/__init__.py
pogger-0.1.14.dist-info/METADATA
pogger-0.1.14.dist-info/WHEEL
pogger-0.1.14.dist-info/RECORD
